LICENSE
MANIFEST.in
README.rst
VERSION
setup.py
src/photo2cnccut/__init__.py
src/photo2cnccut/base.py
src/photo2cnccut/line.py
src/photo2cnccut/ui.py
src/photo2cnccut.egg-info/PKG-INFO
src/photo2cnccut.egg-info/SOURCES.txt
src/photo2cnccut.egg-info/dependency_links.txt
src/photo2cnccut.egg-info/entry_points.txt
src/photo2cnccut.egg-info/not-zip-safe
src/photo2cnccut.egg-info/top_level.txt