Metadata-Version: 1.2
Name: photo2cnccut
Version: 0.1.0
Summary: Create g-code from photos.
Home-page: https://github.com/openandclose/photo2cnccut
Author: Open Close
Author-email: openandclose23@gmail.com
License: MIT
Keywords: cnc gcode g-code image photo photovcarve rastercarve
Platform: UNKNOWN
Classifier: Development Status :: 4 - Beta
Classifier: Intended Audience :: Manufacturing
Classifier: License :: OSI Approved :: MIT License
Classifier: Programming Language :: Python :: 3 :: Only
Classifier: Programming Language :: Python :: 3.6
Classifier: Programming Language :: Python :: 3.7
Classifier: Programming Language :: Python :: 3.8
Classifier: Topic :: Utilities
Requires-Python: ~=3.6
